{
	"name": "Get Table from OnPrem",
	"properties": {
		"activities": [
			{
				"name": "Copy data1",
				"type": "Copy",
				"dependsOn": [],
				"policy": {
					"timeout": "0.12:00:00",
					"retry": 0,
					"retryIntervalInSeconds": 30,
					"secureOutput": false,
					"secureInput": false
				},
				"userProperties": [],
				"typeProperties": {
					"source": {
						"type": "SqlServerSource",
						"queryTimeout": "02:00:00",
						"partitionOption": "None"
					},
					"sink": {
						"type": "ParquetSink",
						"storeSettings": {
							"type": "AzureBlobFSWriteSettings"
						},
						"formatSettings": {
							"type": "ParquetWriteSettings"
						}
					},
					"enableStaging": false,
					"translator": {
						"type": "TabularTranslator",
						"typeConversion": true,
						"typeConversionSettings": {
							"allowDataTruncation": true,
							"treatBooleanAsNumber": false
						}
					}
				},
				"inputs": [
					{
						"referenceName": "DS_SQLServer",
						"type": "DatasetReference",
						"parameters": {
							"SchemaName": "person",
							"TableName": "person",
							"DatabaseName": "AdventureWorks2022"
						}
					}
				],
				"outputs": [
					{
						"referenceName": "DS_ADLS_Parquet",
						"type": "DatasetReference",
						"parameters": {
							"ContainerName": "adventureworks2022",
							"FolderName": "Person",
							"FileName": "PersonPerson"
						}
					}
				]
			}
		],
		"annotations": [],
		"lastPublishTime": "2024-01-30T17:12:40Z"
	},
	"type": "Microsoft.DataFactory/factories/pipelines"
}